<?xml version="1.0" encoding="utf-8"?>
<Patch>
	<Operation Class="PatchOperationFindMod">
		<mods>
			<li>Expanded Materials - Metals</li>
		</mods>
		<match Class="PatchOperationSequence">
			<success>Normal</success>
			<operations>
				<li Class="PatchOperationFindMod">
					<mods>
						<li>Yayo's Combat 3 [Adopted]</li>
					</mods>
					<match Class="PatchOperationSequence">
						<success>Normal</success>
						<operations>

							<!-- Spacer Ammo -->

							<li Class="PatchOperationReplace">
								<xpath>/Defs/RecipeDef[defName = "Make_yy_ammo_spacer"]/ingredients</xpath>
								<value>
									<ingredients>
										<li>
											<filter>
												<thingDefs>
													<li>ComponentIndustrial</li>
												</thingDefs>
											</filter>
											<count>7</count>
										</li>
										<li>
											<filter>
												<thingDefs>
													<li>VMEu_StainlessSteel</li>
												</thingDefs>
											</filter>
											<count>10</count>
										</li>
                                        <li>
                                            <filter>
                                                <thingDefs>
                                                    <li>VMEu_Lithium</li>
                                                </thingDefs>
                                            </filter>
                                            <count>2</count>
                                        </li>
									</ingredients>
								</value>
							</li>
							<li Class="PatchOperationReplace">
								<xpath>/Defs/RecipeDef[defName = "Make_yy_ammo_spacer"or defName="Make_yy_ammo_spacer10"]/fixedIngredientFilter</xpath>
								<value>
									<fixedIngredientFilter>
										<thingDefs>
											<li>ComponentIndustrial</li>
											<li>VMEu_StainlessSteel</li>
											<li>VMEu_Lithium</li>
										</thingDefs>
									</fixedIngredientFilter>
								</value>
							</li>
							<li Class="PatchOperationReplace">
								<xpath>/Defs/RecipeDef[defName = "Make_yy_ammo_spacer10"]/ingredients</xpath>
								<value>
									<ingredients>
										<li>
											<filter>
												<thingDefs>
													<li>ComponentIndustrial</li>
												</thingDefs>
											</filter>
											<count>70</count>
										</li>
										<li>
											<filter>
												<thingDefs>
													<li>VMEu_StainlessSteel</li>
												</thingDefs>
											</filter>
											<count>100</count>
										</li>
										<li>
											<filter>
												<thingDefs>
													<li>VMEu_Lithium</li>
												</thingDefs>
											</filter>
											<count>4</count>
										</li>
									</ingredients>
								</value>
							</li>

							<!-- Spacer Fire/Bomb/Smoke -->

							<li Class="PatchOperationReplace">
								<xpath>/Defs/RecipeDef[defName = "Make_yy_ammo_spacer_fire"]/ingredients</xpath>
								<value>
									<ingredients>
										<li>
											<filter>
												<thingDefs>
													<li>Chemfuel</li>
												</thingDefs>
											</filter>
											<count>6</count>
										</li>
										<li>
											<filter>
												<thingDefs>
													<li>VMEu_StainlessSteel</li>
												</thingDefs>
											</filter>
											<count>6</count>
										</li>
										<li>
											<filter>
												<thingDefs>
													<li>VMEu_Lithium</li>
												</thingDefs>
											</filter>
											<count>2</count>
										</li>
									</ingredients>
								</value>
							</li>
							<li Class="PatchOperationReplace">
								<xpath>/Defs/RecipeDef[defName = "Make_yy_ammo_spacer_fire10"]/ingredients</xpath>
								<value>
									<ingredients>
										<li>
											<filter>
												<thingDefs>
													<li>Chemfuel</li>
												</thingDefs>
											</filter>
											<count>60</count>
										</li>
										<li>
											<filter>
												<thingDefs>
													<li>VMEu_StainlessSteel</li>
												</thingDefs>
											</filter>
											<count>60</count>
										</li>
										<li>
											<filter>
												<thingDefs>
													<li>VMEu_Lithium</li>
												</thingDefs>
											</filter>
											<count>4</count>
										</li>
									</ingredients>
								</value>
							</li>

							<!-- Special Spacer ammo -->

							<li Class="PatchOperationReplace">
								<xpath>/Defs/RecipeDef[defName = "Make_yy_ammo_spacer_emp"]/ingredients</xpath>
								<value>
									<ingredients>
										<li>
											<filter>
												<thingDefs>
													<li>ComponentIndustrial</li>
												</thingDefs>
											</filter>
											<count>6</count>
										</li>
										<li>
											<filter>
												<thingDefs>
													<li>Plasteel</li>
												</thingDefs>
											</filter>
											<count>6</count>
										</li>
										<li>
											<filter>
												<thingDefs>
													<li>VMEu_Lithium</li>
												</thingDefs>
											</filter>
											<count>2</count>
										</li>
									</ingredients>
								</value>
							</li>
							<li Class="PatchOperationReplace">
								<xpath>/Defs/RecipeDef[defName = "Make_yy_ammo_spacer_emp10"]/ingredients</xpath>
								<value>
									<ingredients>
										<li>
											<filter>
												<thingDefs>
													<li>ComponentIndustrial</li>
												</thingDefs>
											</filter>
											<count>60</count>
										</li>
										<li>
											<filter>
												<thingDefs>
													<li>Plasteel</li>
												</thingDefs>
											</filter>
											<count>60</count>
										</li>
										<li>
											<filter>
												<thingDefs>
													<li>VMEu_Lithium</li>
												</thingDefs>
											</filter>
											<count>2</count>
										</li>
									</ingredients>
								</value>
							</li>
						</operations>
					</match>
				</li>
			</operations>
		</match>
	</Operation>
</Patch>